{
  "name": "cargo",
  "ecosystem": "Rust",
  "description": "Rust package manager",
  "commands": {
    "install": "cargo install [package]",
    "uninstall": "cargo uninstall [package]",
    "update": "cargo update [package]",
    "search": "cargo search [query]",
    "info": "cargo info [package]",
    "init": "cargo init",
    "new": "cargo new [name]",
    "add": "cargo add [package]",
    "remove": "cargo remove [package]",
    "run": "cargo run",
    "build": "cargo build",
    "test": "cargo test",
    "bench": "cargo bench",
    "check": "cargo check",
    "doc": "cargo doc",
    "publish": "cargo publish",
    "login": "cargo login",
    "logout": "cargo logout",
    "owner": "cargo owner <subcommand>",
    "yank": "cargo yank [package]",
    "clean": "cargo clean",
    "tree": "cargo tree",
    "fetch": "cargo fetch",
    "package": "cargo package",
    "format": "cargo fmt",
    "version": "cargo version",
    "config": "cargo config",
    "help": "cargo help [command]"
  }
}
